awslabs/__init__.py
awslabs/aws_support_mcp_server/__init__.py
awslabs/aws_support_mcp_server/client.py
awslabs/aws_support_mcp_server/consts.py
awslabs/aws_support_mcp_server/debug_helper.py
awslabs/aws_support_mcp_server/errors.py
awslabs/aws_support_mcp_server/formatters.py
awslabs/aws_support_mcp_server/models.py
awslabs/aws_support_mcp_server/server.py
awslabs_aws_support_mcp_server-0.1.16.dist-info/METADATA
awslabs_aws_support_mcp_server-0.1.16.dist-info/WHEEL
awslabs_aws_support_mcp_server-0.1.16.dist-info/entry_points.txt
awslabs_aws_support_mcp_server-0.1.16.dist-info/top_level.txt
awslabs_aws_support_mcp_server-0.1.16.dist-info/RECORD
