Metadata-Version: 2.4
Name: awslabs.aws-support-mcp-server
Version: 0.1.16
Summary: An Model Context Protocol (MCP) server for AWS SupportAPI.
Author: Amazon Web Services
Author-email: John de Villiers <jackdevilliers.work@gmail.com>
Classifier: License :: OSI Approved :: Apache Software License
Classifier: Operating System :: OS Independent
Classifier: Programming Language :: Python
Classifier: Programming Language :: Python :: 3
Classifier: Programming Language :: Python :: 3.10
Classifier: Programming Language :: Python :: 3.11
Classifier: Programming Language :: Python :: 3.12
Classifier: Programming Language :: Python :: 3.13
Requires-Python: >=3.10
Requires-Dist: boto3>=1.38.12
Requires-Dist: fastmcp>=2.14.0
Requires-Dist: langdetect>=1.0.9
Requires-Dist: loguru>=0.7.0
Requires-Dist: markdownify>=0.13.1
Requires-Dist: mcp[cli]>=1.23.0
Requires-Dist: pre-commit>=4.2.0
Requires-Dist: protego>=0.3.1
Requires-Dist: pydantic>=2.0.0
Requires-Dist: pytest>=8.3.5
Requires-Dist: pytest-asyncio>=0.26.0
Requires-Dist: pytest-cov>=6.1.1
Requires-Dist: readabilipy>=0.2.0
Requires-Dist: requests>=2.32.3
Provides-Extra: dev
Requires-Dist: pytest>=7.0.0; extra == "dev"
Requires-Dist: pytest-asyncio>=0.21.0; extra == "dev"
Requires-Dist: pytest-cov>=4.1.0; extra == "dev"
Requires-Dist: ruff>=0.0.291; extra == "dev"
Requires-Dist: pyright>=1.1.350; extra == "dev"
Requires-Dist: pre-commit>=3.5.0; extra == "dev"
